{
	"payments": {
		"enabled": true,
		"current_issues": [],
		"upcoming_issues": {}
	},
	"payouts": {
		"enabled": false,
		"current_issues": [
			{
				"issue_type": "application_block",
				"application_block": {
					"reason": "This is a sham!"
				},
				"target": {
					"resource": "accounts",
					"id": "f779afd5-f860-43fb-9d19-d47d3b099bf3",
					"path": "/accounts/f779afd5-f860-43fb-9d19-d47d3b099bf3"
				}
			}
		],
		"upcoming_issues": {}
	},
	"terminals": {
		"enabled": true,
		"current_issues": [],
		"upcoming_issues": {}
	},
	"id": null,
	"resource": "capabilities",
	"path": "/accounts/f779afd5-f860-43fb-9d19-d47d3b099bf3/capabilities",
	"owner": {
		"id": "f779afd5-f860-43fb-9d19-d47d3b099bf3",
		"resource": "accounts",
		"path": "/accounts/f779afd5-f860-43fb-9d19-d47d3b099bf3"
	},
	"api_version": "3.0"
}