{
    "additionalProperties": false,
    "properties": {
        "account_id": {
            "type": "string",
            "nullable": false
        },
        "category": {
            "type": "string",
            "enum": [
                "personal",
                "business",
                "cash_management",
                "funds_transfer"
            ],
            "x-enumDescriptions": {
                "personal": "",
                "business": "",
                "cash_management": "",
                "funds_transfer": ""
            }
        },
        "payment_method_id": {
            "type": "string",
            "nullable": false
        },
        "signature": {
            "additionalProperties": false,
            "properties": {
                "signatory_name": {
                    "type": "string",
                    "nullable": false
                },
                "signature_time": {
                    "type": "integer"
                }
            },
            "required": [
                "signatory_name",
                "signature_time"
            ],
            "type": "object"
        },
        "type": {
            "type": "string",
            "enum": [
                "one_time",
                "recurring",
                "sporadic"
            ],
            "x-enumDescriptions": {
                "one_time": "",
                "recurring": "",
                "sporadic": ""
            }
        }
    },
    "type": "object",
    "required": [
        "payment_method_id",
        "account_id",
        "category",
        "type",
        "signature"
    ]
}